README.md
setup.cfg
setup.py
iri90/__init__.py
iri90/plots.py
iri90.egg-info/PKG-INFO
iri90.egg-info/SOURCES.txt
iri90.egg-info/dependency_links.txt
iri90.egg-info/entry_points.txt
iri90.egg-info/requires.txt
iri90.egg-info/top_level.txt
src/iri90.f