Metadata-Version: 2.1
Name: iri90
Version: 1.1.1
Summary: IRI90 from Python, clean and flexible ionospheric model.
Home-page: https://github.com/scivision/iri90
Author: Michael Hirsch, Ph.D.
License: UNKNOWN
Keywords: ionosphere,thermosphere
Platform: UNKNOWN
Classifier: Development Status :: 4 - Beta
Classifier: Environment :: Console
Classifier: Intended Audience :: Science/Research
Classifier: Programming Language :: Python :: 3.6
Classifier: Programming Language :: Python :: 3.7
Classifier: Topic :: Scientific/Engineering :: Atmospheric Science
Requires-Python: >= 3.6
Provides-Extra: plot
Provides-Extra: tests
